signal_tools/__init__.py
signal_tools/cli.py
signal_tools/trapezfilter.py
signal_tools-0.0.1.dist-info/METADATA
signal_tools-0.0.1.dist-info/WHEEL
signal_tools-0.0.1.dist-info/entry_points.txt
signal_tools-0.0.1.dist-info/top_level.txt
signal_tools-0.0.1.dist-info/RECORD
