Metadata-Version: 2.1
Name: signal-tools
Version: 0.0.1
Summary: Command line tool to filter and tranform datastreams
Author: Alexander Becker
Author-email: a.becker@cern.ch
License: GPL3
Keywords: signals,science,math
Classifier: Programming Language :: Python :: 3
Classifier: License :: OSI Approved :: GNU General Public License v3 (GPLv3)
Classifier: Operating System :: POSIX :: Linux
Classifier: Environment :: Console
Requires-Dist: numpy
Requires-Dist: matplotlib
Requires-Dist: PyQt6
